auctions/__init__.py
auctions/rent/__init__.py
auctions/rent/rent_auctions.py
auctions/sale/__init__.py
auctions/sale/sale_auctions.py
dex/__init__.py
dex/erc20.py
dex/master_gardener.py
dex/uniswap_v2_factory.py
dex/uniswap_v2_pair.py
dex/uniswap_v2_router.py
dex/utils/__init__.py
dex/utils/utils.py
dfkpy-0.1.data/scripts/dfkpy
genes/__init__.py
genes/gene_science.py
hero/__init__.py
hero/hero.py
hero/utils/__init__.py
hero/utils/utils.py
meditation/__init__.py
meditation/meditation.py
profile/__init__.py
profile/profile.py
quest/__init__.py
quest/fishing.py
quest/foraging.py
quest/gardening.py
quest/minning.py
quest/quest.py
quest/quest_core.py
quest/wishing_well.py
quest/utils/__init__.py
quest/utils/utils.py
summoning/__init__.py
summoning/crystals.py
summoning/summoning.py
dfkpy-0.1.dist-info/LICENSE
dfkpy-0.1.dist-info/METADATA
dfkpy-0.1.dist-info/WHEEL
dfkpy-0.1.dist-info/top_level.txt
dfkpy-0.1.dist-info/RECORD
