Metadata-Version: 2.1
Name: dfkpy
Version: 0.1
Summary: Python sdk for Defikingdom
Home-page: https://github.com/yurenji/dfk
Author: 0xmars511
Author-email: yurenji@gmail.com
License: UNKNOWN
Platform: UNKNOWN
Classifier: Programming Language :: Python :: 3
Classifier: License :: OSI Approved :: MIT License
Classifier: Operating System :: OS Independent
License-File: LICENSE
